jpprint/__init__.py
jpprint/colors.py
jpprint/core.py
jpprint/formatter.py
jpprint/output.py
jpprint-2.0.3.dist-info/METADATA
jpprint-2.0.3.dist-info/WHEEL
jpprint-2.0.3.dist-info/licenses/LICENSE
jpprint-2.0.3.dist-info/RECORD
