Metadata-Version: 2.4
Name: jpprint
Version: 2.0.3
Summary: Side-by-side JSON comparison tool with color-coded diff indicators
Project-URL: Homepage, https://github.com/voidnologo/jpprint
Project-URL: Repository, https://github.com/voidnologo/jpprint
Author-email: voidnologo <dev@voidnologo.com>
License: MIT
License-File: LICENSE
Keywords: comparison,diff,json,print
Classifier: Development Status :: 4 - Beta
Classifier: Intended Audience :: Developers
Classifier: License :: OSI Approved :: MIT License
Classifier: Programming Language :: Python :: 3
Classifier: Programming Language :: Python :: 3.10
Classifier: Programming Language :: Python :: 3.11
Classifier: Programming Language :: Python :: 3.12
Classifier: Programming Language :: Python :: 3.13
Requires-Python: >=3.10
Provides-Extra: dev
Requires-Dist: isort>=5.12.0; extra == 'dev'
Requires-Dist: ruff>=0.1.0; extra == 'dev'
